openeo_processes/__init__.py
openeo_processes/arrays.py
openeo_processes/comparison.py
openeo_processes/errors.py
openeo_processes/logic.py
openeo_processes/math.py
openeo_processes/texts.py
openeo_processes/utils.py
openeo_processes-0.0.4.dist-info/AUTHORS.rst
openeo_processes-0.0.4.dist-info/LICENSE.txt
openeo_processes-0.0.4.dist-info/METADATA
openeo_processes-0.0.4.dist-info/WHEEL
openeo_processes-0.0.4.dist-info/entry_points.txt
openeo_processes-0.0.4.dist-info/top_level.txt
openeo_processes-0.0.4.dist-info/RECORD
