Metadata-Version: 2.1
Name: openeo-processes
Version: 0.0.4
Summary: Add a short description here!
Home-page: http://...
Author: Claudio Navacchi, Luca Foresta
Author-email: claudio.navacchi@geo.tuwien.ac.at, luca.foresta@eodc.eu
License: mit
Platform: any
Classifier: Development Status :: 4 - Beta
Classifier: Programming Language :: Python
Requires-Dist: numpy
Requires-Dist: pandas
Provides-Extra: dask
Requires-Dist: dask[array] ; extra == 'dask'
Provides-Extra: xarray
Requires-Dist: xarray ; extra == 'xarray'
Requires-Dist: xarray-extras ; extra == 'xarray'
